pygradus/__init__.py
pygradus/api.py
pygradus/attempt.py
pygradus/config.py
pygradus/create.py
pygradus/public.py
pygradus/settings.toml
pygradus-0.6.0.dist-info/LICENSE
pygradus-0.6.0.dist-info/METADATA
pygradus-0.6.0.dist-info/WHEEL
pygradus-0.6.0.dist-info/top_level.txt
pygradus-0.6.0.dist-info/RECORD
