Metadata-Version: 2.1
Name: pygradus
Version: 0.6.0
Summary: Functions to interact with Gradus backend
Home-page: https://pygradus.kiedanski.com
Author: Diego Kiedanski
Author-email: gradus@kiedanski.com
License: MIT
Project-URL: Issue Tracker, https://github.com/wimglenn/resources-example/issues
Keywords: grading,notebooks
License-File: LICENSE
Requires-Dist: setuptools
Requires-Dist: importlib-resources
Requires-Dist: requests
Requires-Dist: dynaconf
Requires-Dist: nbformat
